Metadata-Version: 2.4
Name: youtube-search-next
Version: 1.0.2
Summary: A fork of youtube-search-python. Search for YouTube videos, channels & playlists & get video information using link WITHOUT YouTube Data API v3
Author-email: Sihu Hwang <empathy_noun.6h@icloud.com>
License-Expression: MIT
Project-URL: Homepage, https://github.com/hwangsihu/youtube-search-next
Classifier: Programming Language :: Python :: 3
Classifier: Operating System :: OS Independent
Requires-Python: >=3.6
License-File: LICENSE
Requires-Dist: httpx>=0.14.2
Dynamic: license-file
